{
  "versionCode": 42,
  "versionName": "11.5.6-fullscreen-update-report-fix",
  "apkUrl": "https://github.com/freemoviesforfreepeople/sidi-i-smotri-updates/releases/download/v11.5.6/sidi-i-smotri-11.5.6.apk",
  "sha256": "b9fc70b3faf4a8fe284e96f09feba286064eb2113f518597c3808122822c5ac9",
  "notes": "Исправлено управление Play/Pause в полноэкранном плеере, добавлен автоматический повтор запуска установщика после скачивания обновления и переработана инструкция по передаче диагностического отчёта через QR-код и ссылку."
}
